thirdwave_sdk/__init__.py
thirdwave_sdk/client/__init__.py
thirdwave_sdk/client/base.py
thirdwave_sdk/client/client.py
thirdwave_sdk/models/__init__.py
thirdwave_sdk/models/evm_wallet.py
thirdwave_sdk/models/token.py
thirdwave_sdk/proto/__init__.py
thirdwave_sdk/proto/buf/__init__.py
thirdwave_sdk/proto/buf/validate/__init__.py
thirdwave_sdk/proto/buf/validate/validate_pb2.py
thirdwave_sdk/proto/buf/validate/validate_pb2.pyi
thirdwave_sdk/proto/buf/validate/validate_pb2_grpc.py
thirdwave_sdk/proto/thirdwave/__init__.py
thirdwave_sdk/proto/thirdwave/v1/__init__.py
thirdwave_sdk/proto/thirdwave/v1/evm_pb2.py
thirdwave_sdk/proto/thirdwave/v1/evm_pb2.pyi
thirdwave_sdk/proto/thirdwave/v1/evm_pb2_grpc.py
thirdwave_sdk/proto/thirdwave/v1/evm_wallet_pb2.py
thirdwave_sdk/proto/thirdwave/v1/evm_wallet_pb2.pyi
thirdwave_sdk/proto/thirdwave/v1/evm_wallet_pb2_grpc.py
thirdwave_sdk/services/__init__.py
thirdwave_sdk/services/evm_wallet_service.py
thirdwave_sdk/transport/__init__.py
thirdwave_sdk/transport/interceptors.py
thirdwave_sdk/utils/__init__.py
thirdwave_sdk/utils/eth_utils.py
thirdwave_sdk/utils/get_http_user_agent.py
thirdwave_sdk/utils/proto_module_loader.py
thirdwave_sdk-0.1.15.dist-info/METADATA
thirdwave_sdk-0.1.15.dist-info/WHEEL
thirdwave_sdk-0.1.15.dist-info/RECORD
