Metadata-Version: 2.1
Name: thirdwave-sdk
Version: 0.1.15
Summary: Thirdwave Python SDK for interacting with blockchain wallet intelligence API
Home-page: https://github.com/thirdwaveorg/thirdwave-python-sdk
License: Apache-2.0
Author: Lance Rogers
Author-email: lance@thirdwavelabs.com
Requires-Python: >=3.10,<4.0
Classifier: License :: OSI Approved :: Apache Software License
Classifier: Programming Language :: Python :: 3
Classifier: Programming Language :: Python :: 3.10
Classifier: Programming Language :: Python :: 3.11
Classifier: Programming Language :: Python :: 3.12
Requires-Dist: dnspython (>=2.7.0,<3.0.0)
Requires-Dist: grpc-stubs (>=1.53.0.5,<2.0.0.0)
Requires-Dist: grpcio (>=1.65.4,<2.0.0)
Requires-Dist: grpcio-tools (>=1.65.4,<2.0.0)
Requires-Dist: mypy (>=1.11.0,<2.0.0)
Requires-Dist: mypy-protobuf (>=3.6.0,<4.0.0)
Requires-Dist: protobuf (>=5.27.2,<6.0.0)
Requires-Dist: protovalidate (>=0.3.1,<0.4.0)
Requires-Dist: tomli (>=2.0.2,<3.0.0)
Requires-Dist: types-protobuf (>=5.27.0.20240626,<6.0.0.0)
Project-URL: Repository, https://github.com/thirdwaveorg/thirdwave-python-sdk
